{
  "genres": [
    { "id": "new-jack-swing", "name": "New Jack Swing" },
    { "id": "hip-hop-soul", "name": "Hip-Hop Soul" },
    { "id": "quiet-storm", "name": "Quiet Storm" },
    { "id": "neo-soul", "name": "Neo-Soul" }
  ],
  "vibes": [
    { "id": "slow-jam", "name": "Slow Jam" },
    { "id": "seductive", "name": "Seductive" },
    { "id": "upbeat", "name": "Upbeat" },
    { "id": "chill", "name": "Chill" },
    { "id": "raw", "name": "Raw" },
    { "id": "polished", "name": "Polished" },
    { "id": "groovy", "name": "Groovy" }
  ],
  "grooveTypes": [
    { "id": "swing", "name": "Swing" },
    { "id": "straight", "name": "Straight" },
    { "id": "shuffle", "name": "Shuffle" }
  ],
  "leadInstruments": [
    { "id": "saxophone", "name": "Saxophone" },
    { "id": "rhodes-piano", "name": "Rhodes Piano" },
    { "id": "smooth-electric-guitar", "name": "Smooth Electric Guitar" },
    { "id": "synth-lead", "name": "Synth Lead" }
  ],
  "drumKits": [
    { "id": "acoustic-kit", "name": "Acoustic Kit" },
    { "id": "electronic-kit", "name": "Electronic Kit" },
    { "id": "boom-bap-kit", "name": "90s Boom Bap Kit" },
    { "id": "lo-fi-kit", "name": "Lo-fi Kit" }
  ],
  "bassTones": [
    { "id": "slap", "name": "Slap" },
    { "id": "sub", "name": "Sub" },
    { "id": "synth", "name": "Synth" },
    { "id": "electric", "name": "Electric" }
  ],
  "vocalGenders": [
    { "id": "male", "name": "Male" },
    { "id": "female", "name": "Female" }
  ],
  "harmonyPalettes": [
    { "id": "simple", "name": "Simple" },
    { "id": "gospel", "name": "Gospel" },
    { "id": "jazzy", "name": "Jazzy" },
    { "id": "soulful", "name": "Soulful" }
  ]
} 